vivludo/__init__.py
vivludo/automata.py
vivludo/render.py
vivludo/utils.py
vivludo-0.0.1.dist-info/LICENCE.txt
vivludo-0.0.1.dist-info/METADATA
vivludo-0.0.1.dist-info/WHEEL
vivludo-0.0.1.dist-info/top_level.txt
vivludo-0.0.1.dist-info/RECORD
