Metadata-Version: 2.1
Name: vivludo
Version: 0.0.1
Summary: A cellular automaton library.
Home-page: https://github.com/averyhiebert/vivludo
Author: Avery Hiebert
Author-email: averyhiebert@gmail.com
License: MIT
Platform: UNKNOWN
Classifier: Programming Language :: Python :: 3
Classifier: License :: OSI Approved :: MIT License
Classifier: Operating System :: OS Independent
Requires-Python: >=3.5
Requires-Dist: numpy
Requires-Dist: scipy
Requires-Dist: imageio
